COPYING
MANIFEST.in
README
health_surgery_report.xml
health_surgery_view.xml
setup.py
./__init__.py
./health_surgery.py
./health_surgery_report.xml
./health_surgery_view.xml
./tryton.cfg
./data/health_surgery_sequence.xml
./doc/index.rst
./icons/surgery.svg
./locale/ar.po
./locale/de.po
./locale/el.po
./locale/es.po
./locale/fr.po
./locale/it_IT.po
./locale/ja_JP.po
./locale/lo.po
./locale/pt_BR.po
./locale/zh_CN.po
./report/__init__.py
./report/surgery_report.odt
./report/surgery_report.py
./security/access_rights.xml
./tests/__init__.py
./tests/test_health_surgery.py
./view/gnuhealth_operation.xml
./view/gnuhealth_operation_tree.xml
./view/gnuhealth_patient.xml
./view/gnuhealth_procedure.xml
./view/gnuhealth_procedure_tree.xml
./view/gnuhealth_rcri_form.xml
./view/gnuhealth_rcri_tree.xml
./view/gnuhealth_surgery.xml
./view/gnuhealth_surgery_supply.xml
./view/gnuhealth_surgery_supply_tree.xml
./view/gnuhealth_surgery_team.xml
./view/gnuhealth_surgery_team_tree.xml
./view/gnuhealth_surgery_tree.xml
data/health_surgery_sequence.xml
icons/surgery.svg
locale/ar.po
locale/de.po
locale/el.po
locale/es.po
locale/fr.po
locale/it_IT.po
locale/ja_JP.po
locale/lo.po
locale/pt_BR.po
locale/zh_CN.po
report/surgery_report.odt
security/access_rights.xml
trytond_health_surgery.egg-info/PKG-INFO
trytond_health_surgery.egg-info/SOURCES.txt
trytond_health_surgery.egg-info/dependency_links.txt
trytond_health_surgery.egg-info/entry_points.txt
trytond_health_surgery.egg-info/not-zip-safe
trytond_health_surgery.egg-info/requires.txt
trytond_health_surgery.egg-info/top_level.txt
view/gnuhealth_operation.xml
view/gnuhealth_operation_tree.xml
view/gnuhealth_patient.xml
view/gnuhealth_procedure.xml
view/gnuhealth_procedure_tree.xml
view/gnuhealth_rcri_form.xml
view/gnuhealth_rcri_tree.xml
view/gnuhealth_surgery.xml
view/gnuhealth_surgery_supply.xml
view/gnuhealth_surgery_supply_tree.xml
view/gnuhealth_surgery_team.xml
view/gnuhealth_surgery_team_tree.xml
view/gnuhealth_surgery_tree.xml